{"eb6MpT/qkZeNEMa/sCzTcg==":"alex-iby-280624-2000x1333_-2000x1333.jpg","f7NJWIWrHwvZj5/9PbRP8Q==":"aaditya-kalia-332803-1500x1500.jpg","5ZQ68uFqjGi3N6TQ9VUOow==":"diego-ph-254975-1500x1500.jpg","d0DzChPvNpajHRInRGN1HQ==":"gerrie-van-der-walt-338444-2000x2000.jpg","wDDEje1K/LH6qa8Sojs9Lw==":"filip-mroz-250497-1545x2000.jpg","vTlgULsBrZSFvlWnqFNm4A==":"guilherme-stecanella-370401-2000x1333.jpg","sJr3MNeQKWaIhCHPRhjcgg==":"ecommerce-1000x1200.jpg","8h5n1p+Z0Pkz2+AhP8iLOQ==":"03.jpg","DW2oIz9QZUvQGO+hygOTqA==":"basic-1000x1200.jpg","oEC+M68+X+5PY6Blx0Gq0w==":"portfolio-1000x1200.jpg","uSrbpSUaaRW61OOG6uxRWA==":"background1.jpg","nPTYtIxt7mTU8RlKAbv0eA==":"one-page-1000x1200.jpg","yo5uLYh7acyH4qY8NpCvAw==":"layout-1000x1200.jpg","xTL2HGeb2fZ4Dj78tvDa/A==":"landing-page-1000x1200.jpg","r6yK02UhzEWSbxvUFZVB9w==":"background3.jpg","XrIif4lIrUZbkBnnrdu69w==":"header-800x1200.jpg","R0MNefFMmsCrH6HTPnrw6g==":"amp-menu-800x1200.jpg","SnPtkMKyy9qPTWSRDY49iA==":"footer-800x1200.jpg","BMJGb898uBJKTRjZl+9HBQ==":"map-800x1200.jpg","sbd84mL+BKS1QepufXvQqw==":"video-800x1200.jpg","bptCmzPmr+ttkfWI6ez2Iw==":"images-800x1200.jpg","AALIOqRKvR+onmjc8JpAtQ==":"amp-navigation-800x1200.jpg","25yIiGn3cv3e3IfIRMdnLA==":"article-1-800x1200.jpg","Qsl8rWcDUYthUx+c3jm8ZA==":"f-1489x838.jpg","g4PtY+w9ViIacagU4NnXrg==":"mbr-1920x1275.jpg","69PZ7P0H23XGNOWH8m3lbQ==":"diego-ph-254976-1500x1500.jpg","J5Rf1NRcNcbfuWcSKPZp0A==":"mbr-1920x1276.jpg","YHbdB41Joa0C/skKtqJQfA==":"mbr-700x424.jpg","RBSfRVZnoNCsF5WY2zkGnQ==":"mbr-1-700x424.jpg","YZwcFgNBKkt+Q0UYaRWvNQ==":"mbr-700x467.jpg","DldXHhtUxpO/zLJOGUl3Dg==":"mbr-700x389.jpg","kl/cEC4Eu+XDCrgLG7ckPQ==":"mbr-1-700x389.jpg","c7UvYNZVAFlD2xNNCf6/lA==":"mbr-2-700x389.jpg","lpxmciuF84VZ/b4QEPSB1A==":"mbr-3-700x389.jpg","lZcnkYAHhSbUerIi3jr8ww==":"mbr-4-700x389.jpg","GXBG+RDyO5/QQCRoJ2xGGQ==":"mbr-5-700x389.jpg","ABx8UazafIrD5lvB4VkDpQ==":"mbr-1-700x467.jpg","3mKz6y4nsGoIlW5qfrbMwg==":"mbr-2-700x467.jpg","IBOMdlwiQPGry5pnlTr1cg==":"mbr-3-700x467.jpg","PzZ4kABN7eJ3FIH79ICxwA==":"mbr-4-700x467.jpg","jZ25whvYoT7mBxJBAgeyjw==":"total-media-digital-%20and-mobile-internet-ad-spending-in-india-2013_to-2019-620x418.jpg","WKzazCb4TAtsOyJBgnB7og==":"mbr-1920x1280.jpg","cOZ3tVtV9GogdTHNM9V4zQ==":"digital%20india-820x546.jpg","imI1+S55iwOxfqcMtJPNEA==":"teens-robot-future-science-39349-1280x853.jpg","8ZvFAoGCTwYz6dlVegnL+Q==":"teens-robot-future-science-39350-1280x853.jpg","TYopYv0XmypBH5gpY2v4fA==":"mbr-1080x720.jpg","K4tiZKJcRt+PpANU96qy1A==":"mbr-1080x884.jpg","Hayxf9a7e73HFErq8/GlLw==":"mbr-1920x1536.jpg","4M7Fm/T1Hl6KG7wHLYh4ug==":"logo1.png","gsnUHoxPYjiQJP4tvRLEIQ==":"digital-india-510x364.jpg","VG/zQo9e1C0cm+jXgSljzg==":"background3.jpg","s7AaBqtJmCpmptmO5IdBqA==":"background4.jpg","BRwYqQoQ0Lv+R3vEP9+Ipw==":"mbr-510x360.jpg","iEoDJVtg7HYpRtpVWZtrfw==":"mbr-510x339.jpg","qBAVmhtsxwNfP8rdg5KF6g==":"sameer-meher-300x628.jpg","hWUzdi8P8I7weAjo5luvUg==":"mbr-510x340.jpg","SyLDulqzujjOxDZmgEhy/w==":"mbr-1-510x340.jpg","tYGT7eRZypc7ZqV6Bhy8Gg==":"mbr-510x306.jpg","E/RxT4wqC8/f/Bw8k1cQvQ==":"mbr-510x361.jpg","T0ONLoUen1Aj+s1AkFNqTg==":"mbr-2-510x340.jpg","sR8Jjcam14qR03mw2bTRJg==":"mbr-1920x1357.jpg","M4d75ogyCDMtIcsPs1RVsg==":"mbr-1920x1271.jpg","bRBNjQZSdHIVloJNtnGSow==":"mbr-510x227.jpg","bMGFLzLUWOeIvIGLiXyjxA==":"teens-robot-future-science-39351-1280x853.jpg","M0yC13iUct42oD6SaT0DSQ==":"mbr-1920x1440.jpg","L40HxUR8WWEPtdR6hG57Ow==":"mbr-3-510x340.jpg","4LcbmLE2q19lUDoQ85QLqA==":"mbr-4-510x340.jpg","qEqDeKcLtLpD4PYYhHKCWA==":"mbr-1-1920x1536.jpg","IhyVpS41QBQ6EGIiUOn2qg==":"mbr-5-510x340.jpg","g1/T3QxdEao5hKf2ey09Cw==":"mbr-6-510x340.jpg"}